pysharty/__init__.py
pysharty/board.py
pysharty/file.py
pysharty/post.py
pysharty/thread.py
pysharty/url.py
pysharty/util.py
pysharty-0.6.5.dist-info/LICENSE
pysharty-0.6.5.dist-info/METADATA
pysharty-0.6.5.dist-info/WHEEL
pysharty-0.6.5.dist-info/top_level.txt
pysharty-0.6.5.dist-info/RECORD
